pfe/__init__.py
pfe/comparison.py
pfelogic-2023.5.6.0.dist-info/LICENSE
pfelogic-2023.5.6.0.dist-info/METADATA
pfelogic-2023.5.6.0.dist-info/WHEEL
pfelogic-2023.5.6.0.dist-info/top_level.txt
pfelogic-2023.5.6.0.dist-info/RECORD
