Metadata-Version: 2.1
Name: pfelogic
Version: 2023.5.6.0
Summary: An opinionated pass fail exempt library that I wanted to stop making in every project.
Author-email: Chris Halbersma <chalbersma@halbersma.us>
License: BSD-2-Clause
Keywords: manowar
Classifier: Programming Language :: Python :: 3
Requires-Python: >=3.9
License-File: LICENSE
Requires-Dist: packaging
Requires-Dist: pyjq
